ta_lib_everywhere-0.6.6.dist-info/licenses/AUTHORS
ta_lib_everywhere-0.6.6.dist-info/licenses/LICENSE
talib/__init__.py
talib/_abstract.pxi
talib/_common.pxi
talib/_func.pxi
talib/_stream.pxi
talib/_ta_lib.c
talib/_ta_lib.cp312-win32.pyd
talib/_ta_lib.pyi
talib/_ta_lib.pyx
talib/abstract.py
talib/deprecated.py
talib/py.typed
talib/stream.py
ta_lib_everywhere-0.6.6.dist-info/METADATA
ta_lib_everywhere-0.6.6.dist-info/WHEEL
ta_lib_everywhere-0.6.6.dist-info/top_level.txt
ta_lib_everywhere-0.6.6.dist-info/RECORD
