Metadata-Version: 2.1
Name: ta-lib-everywhere
Version: 0.6.6
Summary: Compiled whls of TA-Lib
Home-page: https://github.com/koreal6803/ta-lib-everywhere
Author: Cheng-Yu Han
Author-email: cheng-yu.han@finlab.tw
License: BSD
Classifier: License :: OSI Approved :: BSD License
Classifier: Development Status :: 5 - Production/Stable
Classifier: Operating System :: Unix
Classifier: Operating System :: POSIX
Classifier: Operating System :: MacOS :: MacOS X
Classifier: Operating System :: Microsoft :: Windows
Classifier: Programming Language :: Python :: 3.10
Classifier: Programming Language :: Python :: 3.11
Classifier: Programming Language :: Python :: 3.12
Classifier: Programming Language :: Python :: 3.13
Classifier: Programming Language :: Cython
Classifier: Topic :: Office/Business :: Financial
Classifier: Topic :: Scientific/Engineering :: Mathematics
Classifier: Intended Audience :: Developers
Classifier: Intended Audience :: Science/Research
Classifier: Intended Audience :: Financial and Insurance Industry
License-File: LICENSE
License-File: AUTHORS
Requires-Dist: numpy>=2.0
